optik/__init__.py
optik/__init__.pyi
optik/optik.abi3.so
optik/py.typed
optik_py-0.5.0.dist-info/METADATA
optik_py-0.5.0.dist-info/WHEEL
optik_py-0.5.0.dist-info/licenses/LICENSE-APACHE
optik_py-0.5.0.dist-info/licenses/LICENSE-MIT
optik_py-0.5.0.dist-info/RECORD
