Metadata-Version: 2.4
Name: optik-py
Version: 0.5.0
Classifier: Topic :: Scientific/Engineering
License-File: LICENSE-APACHE
License-File: LICENSE-MIT
Summary: An optimizing IK solver based on the Lie group of rigid transforms SE(3)
Author: Kyle Cesare
Author-email: kcesare@gmail.com
License-Expression: MIT OR Apache-2.0
Requires-Python: >=3.8
Project-URL: homepage, https://github.com/kylc/optik
